odoo/addons/fieldservice_sale_stock/README.rst
odoo/addons/fieldservice_sale_stock/__init__.py
odoo/addons/fieldservice_sale_stock/__manifest__.py
odoo/addons/fieldservice_sale_stock/i18n/es.po
odoo/addons/fieldservice_sale_stock/i18n/es_AR.po
odoo/addons/fieldservice_sale_stock/i18n/es_CL.po
odoo/addons/fieldservice_sale_stock/i18n/fieldservice_sale_stock.pot
odoo/addons/fieldservice_sale_stock/i18n/it.po
odoo/addons/fieldservice_sale_stock/i18n/pt_BR.po
odoo/addons/fieldservice_sale_stock/models/__init__.py
odoo/addons/fieldservice_sale_stock/models/sale_order.py
odoo/addons/fieldservice_sale_stock/readme/CONFIGURE.md
odoo/addons/fieldservice_sale_stock/readme/CONTRIBUTORS.md
odoo/addons/fieldservice_sale_stock/readme/DESCRIPTION.md
odoo/addons/fieldservice_sale_stock/readme/ROADMAP.md
odoo/addons/fieldservice_sale_stock/readme/USAGE.md
odoo/addons/fieldservice_sale_stock/static/description/icon.png
odoo/addons/fieldservice_sale_stock/static/description/icon.svg
odoo/addons/fieldservice_sale_stock/static/description/index.html
odoo/addons/fieldservice_sale_stock/tests/__init__.py
odoo/addons/fieldservice_sale_stock/tests/test_fsm_sale_order.py
odoo_addon_fieldservice_sale_stock-18.0.1.0.0.3.dist-info/METADATA
odoo_addon_fieldservice_sale_stock-18.0.1.0.0.3.dist-info/WHEEL
odoo_addon_fieldservice_sale_stock-18.0.1.0.0.3.dist-info/top_level.txt
odoo_addon_fieldservice_sale_stock-18.0.1.0.0.3.dist-info/RECORD
