Metadata-Version: 2.1
Name: odoo-addon-fieldservice_sale_stock
Version: 18.0.1.0.0.3
Requires-Python: >=3.10
Requires-Dist: odoo-addon-fieldservice_sale==18.0.*
Requires-Dist: odoo-addon-fieldservice_stock==18.0.*
Requires-Dist: odoo==18.0.*
Summary: Sell stockable items linked to field service orders.
Home-page: https://github.com/OCA/field-service
License: AGPL-3
Author: Brian McMaster, Odoo Community Association (OCA)
Author-email: support@odoo-community.org
Classifier: Programming Language :: Python
Classifier: Framework :: Odoo
Classifier: Framework :: Odoo :: 18.0
Classifier: License :: OSI Approved :: GNU Affero General Public License v3
Classifier: Development Status :: 4 - Beta
